Workbook

Sheet RESUMEN SUPERFICIES
O4: VERSION 25
C5: DUNAMAR | O5: P.E.
O6: 43752
C8: FICHA ARQUITECTONICA
C10: COMUNA: | D10: CONCON
C12: CERTIFICADO DE INFORMES PREVIOS N° | F12: 3032/3033 | H12: PLANO REFERENCIA: | J12: 07. DESARROLLO\01. ARQUITECTURA\01. A0\100-V25-DUNAMAR PLANTAS-14-10-19.dwg
C14: CONDICIONES DE EDIFICACION
C16: Zona de Edificacion | E16: ZVCM-H7 | I16: DISTANCIAMIENTOS | M16: NOTAS:
C17: Rasante | E17: 70° | I17: Antejardin | K17: 5 | M17: 1, LA CABIDA SE HACE CON INFORMES PREVIOS
I18: Dist. Medianeros | K18: 4
C19: Densidad Maxima | E19: 980 | F19: Hab/ha | I19: Dist. Antejardin Subterraneo | K19: 5 | M19: 2, LA CABIDA SE HACE CON PLANO TOPOGRAFICO
I20: Dist. Medianeros Subterraneo | K20: 1
C21: Maximo Ocupacion de suelo | E21: 0.3
C22: Maximo Ocupacion de Pisos Superiores | E22: 0 | I22: PROPUESTA
C23: Superficie Predial Minima | E23: 1000 | I23: N° de Pisos | K23: 22
C24: Constructibilidad | E24: 2 | I24: Altura piso 1° | K24: 2.52
C25: Premio Fusion o C.A. (30% - 50%) | D25: 0.3 | E25: =E24*D25 -> 0.6 | I25: Altura piso tipo | K25: 2.52
C26: TOTAL | E26: =SUM(E24:E25) -> 2.6 | I26: Altura Subterraneo 1 | K26: 2.88
I27: Altura Subterraneo 2
C28: Altura max (pisos) | E28: 20 | I28: Altura Subterraneo 3 | K28: -
C29: Premio 25% C.A. | D29: 0 | E29: =E28*D29 -> 0 | I29: Altura npt 1° Nivel acceso | K29: 0.15
C30: Piso Recogido | E30: 0 | I30: Altura total Edificio | K30: =K25*K23 -> 55.44
C31: TOTAL | E31: =SUM(E28:E30) -> 20 | I31: Altura a enterrarse | K31: 1.44
I32: Altura total sobre N.T.N. | K32: =K30-K31+1 -> 55
C33: Superficie terreno | E33: 5312 | F33: m2
C34: Area Afecta a Utilidad Publica | E34: 0 | F34: m2
C35: Superficie Neta | E35: =E33-E34 -> 5312 | F35: m2
C36: Constructibilidad max permitida | E36: =E35*E26 -> 13811.2 | F36: m2
C37: Superficie Media Calzada | E37: =664.24+1992.78 -> 2657.02 | F37: m2
C38: Superficie para Densidad | E38: =E35+E37 -> 7969.02 | F38: m2
C39: Numero de vivendas permitidas | E39: =((E19*E38)/10000)/4 -> 195.24099 | F39: un
C40: Media departamentos | E40: =E36/E39 -> 70.739244 | F40: m2
C45: CUADROS DE SUPERFICIES EDIFICIO VIVIENDA
C48: PISOS | D48: Superficie Municipal x Recinto
D49: Int Dpto | E49: Loggia | F49: Bodegas y Est. Mun. | G49: Total Util | H49: Subterraneos | I49: Terraza | J49: Area | K49: Total Comun | L49: TOTAL
D50: Municipal | E50: Municipal | I50: Municipal | J50: Comun | K50: Municipal
D51: m2 | E51: m2 | F51: m2 | G51: m2 | H51: m2 | I51: m2 | J51: m2 | K51: m2 | L51: m2
C52: Subterraneo 3 | D52: =D93 -> 500.13 | G52: =SUM(D52:F52) -> 500.13 | H52: =I93+G93+H93 -> 1000.26 | L52: =G52+H52 -> 1500.39
C53: Subterraneo 2 | G53: =SUM(D53:F53) -> 0 | H53: =I94+G94 -> 2255.63 | L53: =+G53+H53+K53 -> 2255.63
C54: Subterraneo 1 | G54: =SUM(D54:F54) -> 0 | H54: =I95+G95 -> 2211.41 | L54: =+G54+H54+K54 -> 2211.41
C55: =C96 -> Piso N° 1 | D55: =($F$157*D182)+($F$158*E182)+($M$159*F182)+($F$160*G182)+($F$161*H182)+($F$164*I182)+($F$165*J182)+($F$166*K182)+($F$167*L182)+($F$168*M182)+($F$169*N182) -> 0 | F55: =V144+W142 -> 258.65 | G55: =SUM(D55:F55) -> 258.65 | I55: =($H$157*D182)+($H$158*E182)+($M$159*F182)+($H$160*G182)+($H$161*H182)+($H$162*I182)+($H$163*J182)+($H$164*K182) -> 0 | J55: =W141 -> 250.47 | K55: =J55+I55 -> 250.47 | L55: =+G55+H55+K55 -> 509.12
C56: =C97 -> Piso N° 2 | D56: =($F$157*D183)+($F$158*E183)+($M$159*F183)+($F$160*G183)+($F$161*H183)+($F$162*I183)+($F$163*J183)+($F$164*K183) -> 268.99 | F56: =V149 -> 82.76 | G56: =SUM(D56:F56) -> 351.75 | I56: =($H$157*D183)+($H$158*E183)+($M$159*F183)+($H$160*G183)+($H$161*H183)+($H$162*I183)+($H$163*J183)+($H$164*K183) -> 0 | J56: =W146 -> 196.94 | K56: =J56+I56 -> 196.94 | L56: =+G56+H56+K56 -> 548.69
C57: =C98 -> Piso N° 3 | D57: =($F$157*D184)+($F$158*E184)+($M$159*F184)+($F$160*G184)+($F$161*H184)+($F$162*I184)+($F$163*J184)+($F$164*K184) -> 473.31 | F57: =G98 -> 0 | G57: =SUM(D57:F57) -> 473.31 | I57: =($H$157*D184)+($H$158*E184)+($H$159*F184)+($H$160*G184)+($H$161*H184)+($H$162*I184)+($H$163*J184)+($H$164*K184) -> 0 | J57: =V151 -> 88.18 | K57: =J57+I57 -> 88.18 | L57: =+G57+H57+K57 -> 561.49
C58: =C99 -> Piso N° 4 | D58: =D57 -> 473.31 | F58: =G99 -> 0 | G58: =SUM(D58:F58) -> 473.31 | I58: =I57 -> 0 | J58: =J57 -> 88.18 | K58: =J58+I58 -> 88.18 | L58: =+G58+H58+K58 -> 561.49
C59: =C100 -> Piso N° 5 | D59: =D58 -> 473.31 | F59: =G100 -> 0 | G59: =SUM(D59:F59) -> 473.31 | I59: =I58 -> 0 | J59: =J58 -> 88.18 | K59: =J59+I59 -> 88.18 | L59: =+G59+H59+K59 -> 561.49 | N59: Carga Ocupacion | T59: NºPERSONAS
C60: =C101 -> Piso N° 6 | D60: =D59 -> 473.31 | F60: =G101 -> 0 | G60: =SUM(D60:F60) -> 473.31 | I60: =I59 -> 0 | J60: =J59 -> 88.18 | K60: =J60+I60 -> 88.18 | L60: =+G60+H60+K60 -> 561.49 | N60: =C157 -> DEPTO-A | O60: =J157 -> 1263.12 | P60: =O60/15 -> 84.208 | T60: 0-50 | U60: 1 escaleras 1,1 m
C61: =C102 -> Piso N° 7 | D61: =D60 -> 473.31 | F61: =G102 -> 0 | G61: =SUM(D61:F61) -> 473.31 | I61: =I60 -> 0 | J61: =J60 -> 88.18 | K61: =J61+I61 -> 88.18 | L61: =+G61+H61+K61 -> 561.49 | N61: =C158 -> DEPTO-B | O61: =J158 -> 2007.2 | P61: =O61/15 -> 133.81333 | T61: 51-100 | U61: 1 escaleras 1,2 m
C62: =C103 -> Piso N° 8 | D62: =D61 -> 473.31 | F62: =G103 -> 0 | G62: =SUM(D62:F62) -> 473.31 | I62: =I61 -> 0 | J62: =J61 -> 88.18 | K62: =J62+I62 -> 88.18 | L62: =+G62+H62+K62 -> 561.49 | N62: =#REF! -> #REF! | O62: =#REF! -> #REF! | P62: =O62/15 -> #REF! | T62: 101-150 | U62: 1 escaleras 1,3 m
C63: =C104 -> Piso N° 9 | D63: =D62 -> 473.31 | F63: =G104 -> 0 | G63: =SUM(D63:F63) -> 473.31 | I63: =I62 -> 0 | J63: =J62 -> 88.18 | K63: =J63+I63 -> 88.18 | L63: =+G63+H63+K63 -> 561.49 | N63: =C160 -> DEPTO-C2 | O63: =J160 -> 1005.6 | P63: =O63/15 -> 67.04 | T63: 151-200 | U63: 1 escaleras 1,4 m
C64: =C105 -> Piso N° 10 | D64: =D63 -> 473.31 | F64: =G105 -> 0 | G64: =SUM(D64:F64) -> 473.31 | I64: =I63 -> 0 | J64: =J63 -> 88.18 | K64: =J64+I64 -> 88.18 | L64: =+G64+H64+K64 -> 561.49 | N64: =C161 -> DEPTO-D | O64: =J161 -> 2249.13 | P64: =O64/15 -> 149.942 | T64: 201-250 | U64: 1 escaleras 1,5 m
C65: =C106 -> Piso N° 11 | D65: =D64 -> 473.31 | F65: =G106 -> 0 | G65: =SUM(D65:F65) -> 473.31 | I65: =I64 -> 0 | J65: =J64 -> 88.18 | K65: =J65+I65 -> 88.18 | L65: =+G65+H65+K65 -> 561.49 | T65: 251-300 | U65: 2 escaleras 1,2 m
C66: =C107 -> Piso N° 12 | D66: =D65 -> 473.31 | F66: =G107 -> 0 | G66: =SUM(D66:F66) -> 473.31 | I66: =I65 -> 0 | J66: =J65 -> 88.18 | K66: =J66+I66 -> 88.18 | L66: =+G66+H66+K66 -> 561.49 | T66: 301-400 | U66: 2 escaleras 1,3 m
C67: =C108 -> Piso N° 13 | D67: =D66 -> 473.31 | F67: =G108 -> 0 | G67: =SUM(D67:F67) -> 473.31 | I67: =I66 -> 0 | J67: =J66 -> 88.18 | K67: =J67+I67 -> 88.18 | L67: =+G67+H67+K67 -> 561.49 | N67: TOTAL | P67: =SUM(P60:P66) -> #REF! | T67: 401-500 | U67: 2 escaleras 1,4 m
C68: =C109 -> Piso N° 14 | D68: =D67 -> 473.31 | F68: =G109 -> 0 | G68: =SUM(D68:F68) -> 473.31 | I68: =I67 -> 0 | J68: =J67 -> 88.18 | K68: =J68+I68 -> 88.18 | L68: =+G68+H68+K68 -> 561.49 | N68: 2 escaleras 1,6 m | T68: 501-700 | U68: 2 escaleras 1,5 m
C69: =C110 -> Piso N° 15 | D69: =D68 -> 473.31 | F69: =G110 -> 0 | G69: =SUM(D69:F69) -> 473.31 | I69: =I68 -> 0 | J69: =J68 -> 88.18 | K69: =J69+I69 -> 88.18 | L69: =+G69+H69+K69 -> 561.49 | T69: 701-1000 | U69: 2 escaleras 1,6 m
C70: =C111 -> Piso N° 16 | D70: =D69 -> 473.31 | F70: =G113 -> 0 | G70: =SUM(D70:F70) -> 473.31 | I70: =I69 -> 0 | J70: =J69 -> 88.18 | K70: =J70+I70 -> 88.18 | L70: =+G70+H70+K70 -> 561.49
C71: =C112 -> Piso N° 17 | D71: =D70 -> 473.31 | F71: =G111 -> 0 | G71: =SUM(D71:F71) -> 473.31 | I71: =I70 -> 0 | J71: =J70 -> 88.18 | K71: =J71+I71 -> 88.18 | L71: =+G71+H71+K71 -> 561.49
C72: =C113 -> Piso N° 18 | D72: =D71 -> 473.31 | F72: =G111 -> 0 | G72: =SUM(D72:F72) -> 473.31 | I72: =I71 -> 0 | J72: =J71 -> 88.18 | K72: =J72+I72 -> 88.18 | L72: =+G72+H72+K72 -> 561.49 | N72: Calculo Areas Comunes (DFL2)
C73: =C114 -> Piso N° 19 | D73: =D72 -> 473.31 | F73: =G112 -> 0 | G73: =SUM(D73:F73) -> 473.31 | I73: =I72 -> 0 | J73: =J72 -> 88.18 | K73: =J73+I73 -> 88.18 | L73: =+G73+H73+K73 -> 561.49 | N73: MAX. 20% = | P73: =D84*0.2 -> 1952.402
C74: =C115 -> Piso N° 20 | D74: =D73 -> 473.31 | F74: =G113 -> 0 | G74: =SUM(D74:F74) -> 473.31 | I74: =I73 -> 0 | J74: =J73 -> 88.18 | K74: =J74+I74 -> 88.18 | L74: =+G74+H74+K74 -> 561.49 | N74: PROPUESTO= | O74: =K84 -> 2307.72 | P74: =K84 -> 2307.72 | Q74: =P74/D84 -> 0.23639804
C75: =C116 -> Piso N° 21 | D75: =D74 -> 473.31 | F75: =G116 -> 0 | G75: =SUM(D75:F75) -> 473.31 | I75: =I74 -> 0 | J75: =J74 -> 88.18 | K75: =J75+I75 -> 88.18 | L75: =+G75+H75+K75 -> 561.49 | N75: PRORRATEO AREAS COMUNES | P75: =P74-P73 -> 355.318 | Q75: =P75/D84 -> 0.036398037
C76: =C117 -> Piso N° 22 | D76: =($F$157*D203)+($F$158*E203)+($M$159*F203)+($F$160*G203)+($F$161*H203)+($F$164*I203)+($F$165*J203)+($F$166*K203)+($F$167*L203)+($F$168*M203)+($F$169*N203) -> 0 | F76: =G117 -> 0 | G76: =SUM(D76:F76) -> 0 | I76: =($H$157*D203)+($H$158*E203)+($H$159*F203)+($H$160*G203)+($H$161*H203)+($H$164*I203)+($H$165*J203)+($H$166*K203)+($H$167*L203)+($H$168*M203)+($H$169*N203) -> 0 | J76: =W156 -> 184.89 | K76: =J76+I76 -> 184.89 | L76: =+G76+H76+K76 -> 184.89 | N76: PROPUESTO FINAL | P76: =P74-P75 -> 1952.402
C78: Cubierta
N80: Coeficiente de ocupacion de suelo
N81: MAX. | O81: =E21 -> 0.3 | P81: =O81*E35 -> 1593.6
N82: PROPUESTO= | O82: =L55 -> 509.12 | P82: =O82/E35 -> 0.095843373
C84: TOTAL | D84: =SUM(D52:D83) -> 9762.01 | E84: =SUM(E52:E83) -> 0 | F84: =SUM(F55:F83) -> 341.41 | G84: =SUM(G55:G83) -> 9603.29 | H84: =SUM(H52:H83) -> 5467.3 | I84: =SUM(I52:I83) -> 0 | J84: =SUM(J55:J83) -> 2307.72 | K84: =SUM(K55:K83) -> 2307.72 | L84: =SUM(L52:L83) -> 17878.44
C85: PORCENTAJE | D85: =+IF($G84=0,0,D84/$L84) -> 0.54602135 | E85: =+IF($G84=0,0,E84/$L84) -> 0 | F85: =+IF($G84=0,0,F84/$L84) -> 0.019096185 | G85: =+IF($G84=0,0,G84/$L84) -> 0.53714362 | I85: =+IF($G84=0,0,I84/$L84) -> 0 | J85: =+J84/F84 -> 6.7593802 | K85: =+K84/G84 -> 0.24030515 | L85: =+IF($G84=0,0,L84/$L84) -> 1
C88: PISOS | D88: Superficies de Losas (al 100%)
D89: Int Dpto | E89: Loggia | F89: Terraza | G89: Bodegas | H89: Total Dpto | I89: Subterraneos | J89: Comun | K89: Escalera | L89: Ascensor | M89: Sup | N89: Porteria | O89: Total
D90: Losa | E90: Losa | F90: Losa | G90: y Est. | J90: Losa | K90: Losa | M90: Cubiertas
D91: m2 | E91: m2 | F91: m2 | G91: m2 | H91: m2 | I91: m2 | J91: m2 | K91: m2 | L91: m2 | M91: m2 | N91: m2 | O91: m2
C93: Subterraneo 3 LOCALES COMERCIALES | D93: =F165 -> 500.13 | G93: =V128+V126 -> 260.54 | H93: =D93 -> 500.13 | I93: =V124-G93 -> 239.59 | O93: =SUM(G93:N93)-L93 -> 1000.26
C94: Subterraneo 2 | G94: =V133+V131 -> 1135.01 | I94: =V130-G94 -> 1120.62 | K94: 22.37 | L94: 11.55 | O94: =SUM(G94:N94)-L94 -> 2278
C95: Subterraneo 1 | G95: =V138+V136 -> 1047.38 | I95: =V135-G95-K95-L95 -> 1164.03 | K95: =32.67 -> 32.67 | L95: =L94 -> 11.55 | O95: =SUM(G95:N95)-L95 -> 2244.08
C96: Piso N° 1 | D96: =($K$157*D182)+($K$158*E182)+($K$159*F182)+($K$160*G182)+($K$161*H182)+($K$162*I182)+($K$163*J182)+($K$164*K182)+($K$165*L182)+($K$166*M182)+($K$167*N182) -> 0 | E96: =($L$157*E219)+($L$158*F219)+($K$159*G219)+($L$160*H219)+($L$161*I219)+($L$164*J219)+($L$165*K219)+($L$166*L219)+($L$167*M219)+($L$168*N219)+($L$169*O219) -> 0 | F96: =($M$157*D182)+($M$158*E182)+($M$159*F182)+($M$160*G182)+($M$161*H182)+($M$164*I182)+($M$165*J182)+($M$166*K182)+($M$167*L182)+($M$168*M182)+($M$169*N182) -> 0 | G96: =V144+V142 -> 422.09 | H96: =SUM(D96:G96) -> 422.09 | J96: =V141 -> 293.09 | K96: =K95 -> 32.67 | L96: =L95 -> 11.55 | O96: =SUM(H96:N96)-L96 -> 747.85
C97: Piso N° 2 | D97: =($K$157*D183)+($K$158*E183)+($K$159*F183)+($K$160*G183)+($K$161*H183)+($K$162*I183)+($K$163*J183)+($K$164*K183) -> 268.99 | E97: =($L$157*E220)+($L$158*F220)+($K$159*G220)+($L$160*H220)+($L$161*I220)+($L$164*J220)+($L$165*K220)+($L$166*L220)+($L$167*M220)+($L$168*N220)+($L$169*O220) -> 0 | F97: =($M$157*D183)+($M$158*E183)+($M$159*F183)+($M$160*G183)+($M$161*H183)+($M$162*I183)+($M$163*J183)+($M$164*K183) -> 44.5 | G97: =V149 -> 82.76 | H97: =SUM(D97:G97) -> 396.25 | J97: =V146 -> 208.24 | K97: =K96 -> 32.67 | L97: =L96 -> 11.55 | O97: =SUM(H97:N97)-L97 -> 637.16
C98: Piso N° 3 | D98: =($K$157*D184)+($K$158*E184)+($K$159*F184)+($K$160*G184)+($K$161*H184)+($K$162*I184)+($K$163*J184)+($K$164*K184) -> 514.5 | E98: =($L$157*E221)+($L$158*F221)+($K$159*G221)+($L$160*H221)+($L$161*I221)+($L$164*J221)+($L$165*K221)+($L$166*L221)+($L$167*M221)+($L$168*N221)+($L$169*O221) -> 0 | F98: =($M$157*D184)+($M$158*E184)+($M$159*F184)+($M$160*G184)+($M$161*H184)+($M$162*I184)+($M$163*J184)+($M$164*K184) -> 88.96 | H98: =SUM(D98:G98) -> 603.46 | J98: =V151 -> 88.18 | K98: =K97 -> 32.67 | L98: =L97 -> 11.55 | O98: =SUM(H98:N98)-L98 -> 724.31
C99: Piso N° 4 | D99: =D98 -> 514.5 | E99: =($L$157*E222)+($L$158*F222)+($K$159*G222)+($L$160*H222)+($L$161*I222)+($L$164*J222)+($L$165*K222)+($L$166*L222)+($L$167*M222)+($L$168*N222)+($L$169*O222) -> 0 | F99: =F98 -> 88.96 | H99: =SUM(D99:G99) -> 603.46 | J99: =J98 -> 88.18 | K99: =K98 -> 32.67 | L99: =L98 -> 11.55 | O99: =SUM(H99:N99)-L99 -> 724.31
C100: Piso N° 5 | D100: =D99 -> 514.5 | E100: =($L$157*E223)+($L$158*F223)+($K$159*G223)+($L$160*H223)+($L$161*I223)+($L$164*J223)+($L$165*K223)+($L$166*L223)+($L$167*M223)+($L$168*N223)+($L$169*O223) -> 0 | F100: =F99 -> 88.96 | H100: =SUM(D100:G100) -> 603.46 | J100: =J99 -> 88.18 | K100: =K99 -> 32.67 | L100: =L99 -> 11.55 | O100: =SUM(H100:N100)-L100 -> 724.31
C101: Piso N° 6 | D101: =D100 -> 514.5 | E101: =($L$157*E224)+($L$158*F224)+($K$159*G224)+($L$160*H224)+($L$161*I224)+($L$164*J224)+($L$165*K224)+($L$166*L224)+($L$167*M224)+($L$168*N224)+($L$169*O224) -> 0 | F101: =F100 -> 88.96 | H101: =SUM(D101:G101) -> 603.46 | J101: =J100 -> 88.18 | K101: =K100 -> 32.67 | L101: =L100 -> 11.55 | O101: =SUM(H101:N101)-L101 -> 724.31
C102: Piso N° 7 | D102: =D101 -> 514.5 | E102: =($L$157*E225)+($L$158*F225)+($K$159*G225)+($L$160*H225)+($L$161*I225)+($L$164*J225)+($L$165*K225)+($L$166*L225)+($L$167*M225)+($L$168*N225)+($L$169*O225) -> 0 | F102: =F101 -> 88.96 | H102: =SUM(D102:G102) -> 603.46 | J102: =J101 -> 88.18 | K102: =K101 -> 32.67 | L102: =L101 -> 11.55 | O102: =SUM(H102:N102)-L102 -> 724.31
C103: Piso N° 8 | D103: =D102 -> 514.5 | E103: =($L$157*E226)+($L$158*F226)+($K$159*G226)+($L$160*H226)+($L$161*I226)+($L$164*J226)+($L$165*K226)+($L$166*L226)+($L$167*M226)+($L$168*N226)+($L$169*O226) -> 0 | F103: =F102 -> 88.96 | H103: =SUM(D103:G103) -> 603.46 | J103: =J102 -> 88.18 | K103: =K102 -> 32.67 | L103: =L102 -> 11.55 | O103: =SUM(H103:N103)-L103 -> 724.31
C104: Piso N° 9 | D104: =D103 -> 514.5 | E104: =($L$157*E227)+($L$158*F227)+($K$159*G227)+($L$160*H227)+($L$161*I227)+($L$164*J227)+($L$165*K227)+($L$166*L227)+($L$167*M227)+($L$168*N227)+($L$169*O227) -> 0 | F104: =F103 -> 88.96 | H104: =SUM(D104:G104) -> 603.46 | J104: =J103 -> 88.18 | K104: =K103 -> 32.67 | L104: =L103 -> 11.55 | O104: =SUM(H104:N104)-L104 -> 724.31
C105: Piso N° 10 | D105: =D104 -> 514.5 | E105: =($L$157*E228)+($L$158*F228)+($K$159*G228)+($L$160*H228)+($L$161*I228)+($L$164*J228)+($L$165*K228)+($L$166*L228)+($L$167*M228)+($L$168*N228)+($L$169*O228) -> 0 | F105: =F104 -> 88.96 | H105: =SUM(D105:G105) -> 603.46 | J105: =J104 -> 88.18 | K105: =K104 -> 32.67 | L105: =L104 -> 11.55 | O105: =SUM(H105:N105)-L105 -> 724.31
C106: Piso N° 11 | D106: =D105 -> 514.5 | E106: =($L$157*E229)+($L$158*F229)+($K$159*G229)+($L$160*H229)+($L$161*I229)+($L$164*J229)+($L$165*K229)+($L$166*L229)+($L$167*M229)+($L$168*N229)+($L$169*O229) -> 0 | F106: =F105 -> 88.96 | H106: =SUM(D106:G106) -> 603.46 | J106: =J105 -> 88.18 | K106: =K105 -> 32.67 | L106: =L105 -> 11.55 | O106: =SUM(H106:N106)-L106 -> 724.31
C107: Piso N° 12 | D107: =D106 -> 514.5 | E107: =($L$157*E230)+($L$158*F230)+($K$159*G230)+($L$160*H230)+($L$161*I230)+($L$164*J230)+($L$165*K230)+($L$166*L230)+($L$167*M230)+($L$168*N230)+($L$169*O230) -> 0 | F107: =F106 -> 88.96 | H107: =SUM(D107:G107) -> 603.46 | J107: =J106 -> 88.18 | K107: =K106 -> 32.67 | L107: =L106 -> 11.55 | O107: =SUM(H107:N107)-L107 -> 724.31
C108: Piso N° 13 | D108: =D107 -> 514.5 | E108: =($L$157*E231)+($L$158*F231)+($K$159*G231)+($L$160*H231)+($L$161*I231)+($L$164*J231)+($L$165*K231)+($L$166*L231)+($L$167*M231)+($L$168*N231)+($L$169*O231) -> 0 | F108: =F107 -> 88.96 | H108: =SUM(D108:G108) -> 603.46 | J108: =J107 -> 88.18 | K108: =K107 -> 32.67 | L108: =L107 -> 11.55 | O108: =SUM(H108:N108)-L108 -> 724.31
C109: Piso N° 14 | D109: =D108 -> 514.5 | E109: =($L$157*E232)+($L$158*F232)+($K$159*G232)+($L$160*H232)+($L$161*I232)+($L$164*J232)+($L$165*K232)+($L$166*L232)+($L$167*M232)+($L$168*N232)+($L$169*O232) -> 0 | F109: =F108 -> 88.96 | H109: =SUM(D109:G109) -> 603.46 | J109: =J108 -> 88.18 | K109: =K108 -> 32.67 | L109: =L108 -> 11.55 | O109: =SUM(H109:N109)-L109 -> 724.31
C110: Piso N° 15 | D110: =D109 -> 514.5 | E110: =($L$157*E233)+($L$158*F233)+($K$159*G233)+($L$160*H233)+($L$161*I233)+($L$164*J233)+($L$165*K233)+($L$166*L233)+($L$167*M233)+($L$168*N233)+($L$169*O233) -> 0 | F110: =F109 -> 88.96 | H110: =SUM(D110:G110) -> 603.46 | J110: =J109 -> 88.18 | K110: =K109 -> 32.67 | L110: =L109 -> 11.55 | O110: =SUM(H110:N110)-L110 -> 724.31
... C116: Piso N° 21 | D116: =D115 -> 514.5 | E116: =($L$157*E239)+($L$158*F239)+($K$159*G239)+($L$160*H239)+($L$161*I239)+($L$164*J239)+($L$165*K239)+($L$166*L239)+($L$167*M239)+($L$168*N239)+($L$169*O239) -> 0 | F116: =F115 -> 88.96 | H116: =SUM(D116:G116) -> 603.46 | J116: =J115 -> 88.18 | K116: =K115 -> 32.67 | L116: =L115 -> 11.55 | O116: =SUM(H116:N116)-L116 -> 724.31
C117: Piso N° 22 | D117: =($K$157*D203)+($K$158*E203)+($K$159*F203)+($K$160*G203)+($K$161*H203)+($K$162*I203)+($K$163*J203)+($K$164*K203)+($K$165*L203)+($K$166*M203)+($K$167*N203) -> 0 | E117: =($L$157*E240)+($L$158*F240)+($K$159*G240)+($L$160*H240)+($L$161*I240)+($L$164*J240)+($L$165*K240)+($L$166*L240)+($L$167*M240)+($L$168*N240)+($L$169*O240) -> 0 | F117: =($M$157*D203)+($M$158*E203)+($M$159*F203)+($M$160*G203)+($M$161*H203)+($M$164*I203)+($M$165*J203)+($M$166*K203)+($M$167*L203)+($M$168*M203)+($M$169*N203) -> 0 | H117: =SUM(D117:G117) -> 0 | J117: =V156 -> 691.57 | K117: =K116 -> 32.67 | L117: =L116 -> 11.55 | O117: =SUM(H117:N117)-L117 -> 724.24
O118: =SUM(H118:N118)-L118 -> 0
C119: Sala de Maquinas | O119: =SUM(H119:N119)-L119 -> 0
O120: =SUM(H120:N120)-L120 -> 0
O121: =SUM(H121:N121)-L121 -> 0
J122: 0 | O122: 0 | V122: LOSA | W122: MUNI
O123: =J123 -> 0
O124: =J124 -> 0 | U124: comercial | V124: ='SUP. DEPARTAMENTOS'!D223 -> 500.13 | Z124: ACTUALIZADO 11-10-2019
C125: TOTAL | D125: =SUM(D94:D124) -> 10044.49 | E125: =SUM(E93:E124) -> 0 | F125: =SUM(F94:F123) -> 1734.74 | G125: =SUM(G93:G123) -> 2947.78 | H125: =SUM(H94:H124) -> 12284.08 | I125: =SUM(I94:I124) -> 2284.65 | J125: =SUM(J94:J124) -> 2868.32 | K125: =SUM(K92:K124) -> 773.78 | L125: =SUM(L94:L124) -> 277.2 | M125: =SUM(M92:M124) -> 0 | N125: =SUM(N92:N124) -> 0 | O125: =SUM(O92:O124) -> 21393.48 | U125: sup. Sub | V125: 575.81
...

Sheet SUP. DEPARTAMENTOS
B2: ='RESUMEN SUPERFICIES'!C5 -> DUNAMAR | G2: ='RESUMEN SUPERFICIES'!O5 -> P.E.
G3: ='RESUMEN SUPERFICIES'!O6 -> 43752
B6: SUPERFICIES DE LOSAS DEPARTAMENTOS
B7: PISO | C7: N° DEPTO | D7: M2 INTERIOR | E7: M2 TERRAZA BALCON | F7: M2 TERRAZA TECHO | G7: M2 TOTAL
B8: 2 | C8: 204 | D8: =D16 -> 50.18 | F8: =F16 -> 8.99 | G8: =SUM(D8:F8) -> 59.17
B9: 2 | C9: 205 | D9: =D17 -> 57.67 | F9: =F17 -> 8.21 | G9: =SUM(D9:F9) -> 65.88
B10: 2 | C10: 207 | D10: =D19 -> 50.18 | F10: =F19 -> 8.99 | G10: =SUM(D10:F10) -> 59.17
B11: 2 | C11: 208 | D11: =D20 -> 60.68 | F11: =F20 -> 9.32 | G11: =SUM(D11:F11) -> 70
B12: 2 | C12: 209 | D12: =D21 -> 50.28 | F12: =F21 -> 8.99 | G12: =SUM(D12:F12) -> 59.27
B13: 3 | C13: 301 | D13: ='RESUMEN SUPERFICIES'!K157 -> 33.24 | F13: ='RESUMEN SUPERFICIES'!M157 -> 7.98 | G13: =SUM(D13:F13) -> 41.22
B14: 3 | C14: 302 | D14: ='RESUMEN SUPERFICIES'!K159 -> 50.18 | F14: ='RESUMEN SUPERFICIES'!M159 -> 8.99 | G14: =SUM(D14:F14) -> 59.17
B15: 3 | C15: 303 | D15: ='RESUMEN SUPERFICIES'!K162 -> 71.18 | F15: ='RESUMEN SUPERFICIES'!M161 -> 8.21 | G15: =SUM(D15:F15) -> 79.39
B16: 3 | C16: 304 | D16: ='RESUMEN SUPERFICIES'!K158 -> 50.18 | F16: ='RESUMEN SUPERFICIES'!M158 -> 8.99 | G16: =SUM(D16:F16) -> 59.17
B17: 3 | C17: 305 | D17: ='RESUMEN SUPERFICIES'!K161 -> 57.67 | F17: ='RESUMEN SUPERFICIES'!M161 -> 8.21 | G17: =SUM(D17:F17) -> 65.88
B18: 3 | C18: 306 | D18: ='RESUMEN SUPERFICIES'!K161 -> 57.67 | F18: ='RESUMEN SUPERFICIES'!M161 -> 8.21 | G18: =SUM(D18:F18) -> 65.88
B19: 3 | C19: 307 | D19: ='RESUMEN SUPERFICIES'!K158 -> 50.18 | F19: ='RESUMEN SUPERFICIES'!M158 -> 8.99 | G19: =SUM(D19:F19) -> 59.17
B20: 3 | C20: 308 | D20: ='RESUMEN SUPERFICIES'!K163 -> 60.68 | F20: ='RESUMEN SUPERFICIES'!M163 -> 9.32 | G20: =SUM(D20:F20) -> 70
B21: 3 | C21: 309 | D21: ='RESUMEN SUPERFICIES'!K160 -> 50.28 | F21: ='RESUMEN SUPERFICIES'!M160 -> 8.99 | G21: =SUM(D21:F21) -> 59.27
B22: 3 | C22: 310 | D22: ='RESUMEN SUPERFICIES'!K157 -> 33.24 | F22: ='RESUMEN SUPERFICIES'!M157 -> 7.98 | G22: =SUM(D22:F22) -> 41.22
B23: 4 | C23: 401 | D23: =D13 -> 33.24 | F23: =F13 -> 7.98 | G23: =SUM(D23:F23) -> 41.22
B24: 4 | C24: 402 | D24: =D14 -> 50.18 | F24: =F14 -> 8.99 | G24: =SUM(D24:F24) -> 59.17
B25: 4 | C25: 403 | D25: =D15 -> 71.18 | F25: =F15 -> 8.21 | G25: =SUM(D25:F25) -> 79.39
B26: 4 | C26: 404 | D26: =D16 -> 50.18 | F26: =F16 -> 8.99 | G26: =SUM(D26:F26) -> 59.17
B27: 4 | C27: 405 | D27: =D17 -> 57.67 | F27: =F17 -> 8.21 | G27: =SUM(D27:F27) -> 65.88
B28: 4 | C28: 406 | D28: =D18 -> 57.67 | F28: =F18 -> 8.21 | G28: =SUM(D28:F28) -> 65.88
B29: 4 | C29: 407 | D29: =D19 -> 50.18 | F29: =F19 -> 8.99 | G29: =SUM(D29:F29) -> 59.17
B30: 4 | C30: 408 | D30: =D20 -> 60.68 | F30: =F20 -> 9.32 | G30: =SUM(D30:F30) -> 70
B31: 4 | C31: 409 | D31: =D21 -> 50.28 | F31: =F21 -> 8.99 | G31: =SUM(D31:F31) -> 59.27
B32: 4 | C32: 410 | D32: =D22 -> 33.24 | F32: =F22 -> 7.98 | G32: =SUM(D32:F32) -> 41.22
B33: 5 | C33: 501 | D33: =D23 -> 33.24 | F33: =F23 -> 7.98 | G33: =SUM(D33:F33) -> 41.22
B34: 5 | C34: 502 | D34: =D24 -> 50.18 | F34: =F24 -> 8.99 | G34: =SUM(D34:F34) -> 59.17
... B182: 19 | C182: 1910 | D182: =D172 -> 33.24 | F182: =F172 -> 7.98 | G182: =SUM(D182:F182) -> 41.22
B183: 20 | C183: 2001 | D183: 33.4 | F183: 9.06 | G183: =SUM(D183:F183) -> 42.46
B184: 20 | C184: 2002 | D184: 50.17 | F184: 13.36 | G184: =SUM(D184:F184) -> 63.53
B185: 20 | C185: 2003 | D185: 72.82 | F185: 15.03 | G185: =SUM(D185:F185) -> 87.85
B186: 20 | C186: 2004 | D186: 50.41 | F186: 13.2 | G186: =SUM(D186:F186) -> 63.61
B187: 20 | C187: 2005 | D187: 57.74 | F187: 16.54 | G187: =SUM(D187:F187) -> 74.28
B188: 20 | C188: 2006 | D188: 57.74 | F188: 16.54 | G188: =SUM(D188:F188) -> 74.28
B189: 20 | C189: 2007 | D189: 50.41 | F189: 13.2 | G189: =SUM(D189:F189) -> 63.61
B190: 20 | C190: 2008 | D190: 72.82 | F190: 15.03 | G190: =SUM(D190:F190) -> 87.85
B191: 20 | C191: 2009 | D191: 50.17 | F191: 13.36 | G191: =SUM(D191:F191) -> 63.53
B192: 20 | C192: 2010 | D192: 33.4 | F192: 9.06 | G192: =SUM(D192:F192) -> 42.46
B193: 21 | C193: 2101 | D193: 33.4 | F193: 9.06 | G193: =SUM(D193:F193) -> 42.46
B194: 21 | C194: 2102 | D194: 50.17 | F194: 13.36 | G194: =SUM(D194:F194) -> 63.53
... B202: 21 | C202: 2110 | D202: 33.4 | F202: 9.06 | G202: =SUM(D202:F202) -> 42.46
B204: TOTAL | D204: =SUM(D8:D202) -> 10073.65 | E204: =SUM(E8:E132) -> 0 | F204: =SUM(F8:F202) -> 1773.05 | G204: =SUM(G8:G202) -> 11846.7 | I204: =G204+500.13 -> 12346.83
B206: SE DEBEN CHEQUEAR SUPERFICIES TOTALES CON DATOS DE RESUMEN, DEBEN SER IDENTICAS
B209: SUPERFICIES DE LOSAS LOCALES COMERCIALES
B210: PISO | C210: N° LOCAL | D210: M2 INTERIOR | E210: M2 TERRAZA BALCON | F210: M2 TERRAZA TECHO | G210: M2 TOTAL
B211: -3 | C211: L.C.01 | D211: 39.24 | F211: 0 | G211: =SUM(D211:F211) -> 39.24
B212: -3 | C212: L.C.02 | D212: 37.48 | F212: 0 | G212: =SUM(D212:F212) -> 37.48
B213: -3 | C213: L.C.03 | D213: 37.48 | F213: 0 | G213: =SUM(D213:F213) -> 37.48
B214: -3 | C214: L.C.04 | D214: 37.48 | F214: 0 | G214: =SUM(D214:F214) -> 37.48
B215: -3 | C215: L.C.05 | D215: 37.36 | F215: 0 | G215: =SUM(D215:F215) -> 37.36
B216: -3 | C216: L.C.06 | D216: 41.2 | F216: 0 | G216: =SUM(D216:F216) -> 41.2
B217: -3 | C217: L.C.07 | D217: 37.69 | F217: 0 | G217: =SUM(D217:F217) -> 37.69
B218: -3 | C218: L.C.08 | D218: 36.96 | F218: 0 | G218: =SUM(D218:F218) -> 36.96
B219: -3 | C219: L.C.09 | D219: 36.96 | F219: 0 | G219: =SUM(D219:F219) -> 36.96
B220: -3 | C220: L.C.10 | D220: 117.7 | F220: 0 | G220: =SUM(D220:F220) -> 117.7
B221: -3 | C221: L.C.11 | D221: 40.58 | F221: 0 | G221: =SUM(D221:F221) -> 40.58
B223: TOTAL | D223: =SUM(D211:D221) -> 500.13 | E223: =SUM(E31:E155) -> 0 | F223: =SUM(F211:F221) -> 0 | G223: =SUM(G211:G221) -> 500.13

Sheet PRODUCTOS SECUNDARIOS
B2: ='RESUMEN SUPERFICIES'!C5 -> DUNAMAR | N2: ='RESUMEN SUPERFICIES'!O5 -> P.E.
N3: ='RESUMEN SUPERFICIES'!O6 -> 43752
B5: BODEGAS INDIVIDUALES | F5: ESTACIONAMIENTOS INDIVIDUALES | K5: VENTA EN CONJUNTO
B6: PISO | C6: N° BODEGA | D6: M2 UTIL MUNICIPAL | F6: PISO | G6: N° ESTACIONAMIENTO | H6: SUPERFICIE | I6: USO | K6: PISO | L6: N° ESTACIONAMIENTO | M6: SUPERFICIE | N6: USO | S6: PISO 2
B7: 2 | C7: B-301 | D7: 3.58 | F7: 1 | G7: EV-01 | H7: 18 | I7: USO Y GOCE EXCLUSIVO | K7: 1 | L7: B-001 | M7: 4.87 | N7: BODEGA | P7: TOTAL BODEGAS P2 | R7: =SUM(D7:D31) -> 82.76
B8: 2 | C8: B-302 | D8: =3.44-0.32 -> 3.12 | F8: 1 | G8: EV-02 | H8: 12.5 | I8: USO Y GOCE EXCLUSIVO | L8: E-25 | M8: 14.81 | N8: ESTACIONAMIENTO
B9: 2 | C9: B-303 | D9: 2.73 | F9: 1 | G9: EV-03 | H9: 12.5 | I9: USO Y GOCE EXCLUSIVO | K9: 1 | L9: B-003 | M9: =3.88-0.33 -> 3.55 | N9: BODEGA | S9: PISO 1
B10: 2 | C10: B-304 | D10: 3.96 | F10: 1 | G10: EV-04 | H10: 12.5 | I10: USO Y GOCE EXCLUSIVO | L10: E-27 | M10: 13.74 | N10: ESTACIONAMIENTO | P10: TOTAL BOD P1 INDV | R10: =SUM(D32:D33) -> 10.35
B11: 2 | C11: B-305 | D11: 3.89 | F11: 1 | G11: EV-05 | H11: 12.5 | I11: USO Y GOCE EXCLUSIVO | K11: 1 | L11: B-004 | M11: 3.65 | N11: BODEGA | P11: TOTAL BOD P1 CONJ | R11: =M7+M9+M11+M13+M15+M17+M19+M21+M23+M25+M27+M29+M31+M33+M35+M37+M39+M41 -> 74.54
B12: 2 | C12: B-306 | D12: 3.31 | F12: 1 | G12: EV-06 | H12: 12.5 | I12: USO Y GOCE EXCLUSIVO | L12: E-28 | M12: 14.21 | N12: ESTACIONAMIENTO
B13: 2 | C13: B-307 | D13: 3.13 | F13: 1 | G13: EV-07 | H13: 12.5 | I13: USO Y GOCE EXCLUSIVO | K13: 1 | L13: B-005 | M13: =3.87-0.34 -> 3.53 | N13: BODEGA | P13: TOTAL BODEGAS P1 | R13: =SUM(R10:R11) -> 84.89
B14: 2 | C14: B-308 | D14: 3.13 | F14: 1 | G14: EV-08 | H14: 12.5 | I14: USO Y GOCE EXCLUSIVO | L14: E-29 | M14: 14.05 | N14: ESTACIONAMIENTO
B15: 2 | C15: B-309 | D15: 3.28 | F15: 1 | G15: EV-09 | H15: 12.5 | I15: USO Y GOCE EXCLUSIVO | K15: 1 | L15: B-006 | M15: =3.89-0.07 -> 3.82 | N15: BODEGA | P15: TOTAL EST P1 INDV | R15: =SUM(H46:H78) -> 442.96
B16: 2 | C16: B-310 | D16: 3.6 | F16: 1 | G16: EV-10 | H16: 12.5 | I16: USO Y GOCE EXCLUSIVO | L16: E-30 | M16: 12.64 | N16: ESTACIONAMIENTO | P16: TOTAL EST P1 CONJ | R16: =M8+M10+M12+M14+M16+M18+M20+M22+M24+M26+M28+M30+M32+M34+M36+M38+M40+M42 -> 250.98
B17: 2 | C17: B-311 | D17: =3.39-0.34 -> 3.05 | F17: 1 | G17: EV-11 | H17: 12.5 | I17: USO Y GOCE EXCLUSIVO | K17: 1 | L17: B-007 | M17: =3.38-0.31 -> 3.07 | N17: BODEGA
B18: 2 | C18: B-312 | D18: =3.8-0.07 -> 3.73 | F18: 1 | G18: EV-12 | H18: 12.5 | I18: USO Y GOCE EXCLUSIVO | L18: E-31 | M18: =15.58-0.19 -> 15.39 | N18: ESTACIONAMIENTO | P18: TOTAL EST P1 | R18: =SUM(R15:R16) -> 693.94
B19: 2 | C19: B-313 | D19: 3.19 | F19: 1 | G19: EV-13 | H19: 12.5 | I19: USO Y GOCE EXCLUSIVO | K19: 1 | L19: B-008 | M19: =3.38-0.31 -> 3.07 | N19: BODEGA
B20: 2 | C20: B-314 | D20: 3.08 | F20: 1 | G20: EV-14 | H20: 12.5 | I20: USO Y GOCE EXCLUSIVO | L20: E-32 | M20: =15.58-0.19 -> 15.39 | N20: ESTACIONAMIENTO | S20: SUBTE. -1
B21: 2 | C21: B-315 | D21: 3.08 | F21: 1 | G21: EV-15 | H21: 12.5 | I21: USO Y GOCE EXCLUSIVO | K21: 1 | L21: B-009 | M21: =3.89-0.07 -> 3.82 | N21: BODEGA | P21: TOTAL BOD SUB1 INDV | R21: =SUM(D34:D35) -> 7.81
B22: 2 | C22: B-316 | D22: 3.22 | F22: 1 | G22: EV-16 | H22: 12.5 | I22: USO Y GOCE EXCLUSIVO | L22: E-33 | M22: 12.64 | N22: ESTACIONAMIENTO | P22: TOTAL BOD SUB1 CONJ | R22: =M43+M45+M47+M49+M51+M53+M55+M57+M59+M61+M63+M65+M67+M69+M71+M73+M75+M77+M79+M81+M83+M85+M87+M89 -> 116.67
B23: 2 | C23: B-317 | D23: =3.51-0.09 -> 3.42 | F23: 1 | G23: EV-17 | H23: 12.5 | I23: USO Y GOCE EXCLUSIVO | K23: 1 | L23: B-010 | M23: =3.87-0.34 -> 3.53 | N23: BODEGA
B24: 2 | C24: B-318 | D24: =3.55-0.28 -> 3.27 | F24: 1 | G24: EV-18 | H24: 12.5 | I24: USO Y GOCE EXCLUSIVO | L24: E-34 | M24: 14.05 | N24: ESTACIONAMIENTO | P24: TOTAL BODEGAS SUB1 | R24: =SUM(R21:R22) -> 124.48
B25: 2 | C25: B-319 | D25: =3.55-0.28 -> 3.27 | F25: 1 | G25: EV-19 | H25: 12.5 | I25: USO Y GOCE EXCLUSIVO | K25: 1 | L25: B-011 | M25: 3.65 | N25: BODEGA
B26: 2 | C26: B-320 | D26: =3.51-0.09 -> 3.42 | F26: 1 | G26: EV-20 | H26: 12.5 | I26: USO Y GOCE EXCLUSIVO | L26: E-35 | M26: 14.21 | N26: ESTACIONAMIENTO | P26: TOTAL EST SUB1 INDV | R26: =SUM(H79:H125) -> 588.62
B27: 2 | C27: B-321 | D27: 3.22 | F27: 1 | G27: EV-21 | H27: 12.5 | I27: USO Y GOCE EXCLUSIVO | K27: 1 | L27: B-012 | M27: =3.88-0.33 -> 3.55 | N27: BODEGA | P27: TOTAL EST SUB1 CONJ | R27: =M44+M46+M48+M50+M52+M54+M56+M58+M60+M62+M64+M66+M68+M70+M72+M74+M76+M78+M80+M82+M84+M86+M88+M90 -> 334.28
B28: 2 | C28: B-322 | D28: 3.08 | F28: 1 | G28: EV-22 | H28: 12.5 | I28: USO Y GOCE EXCLUSIVO | L28: E-36 | M28: 13.74 | N28: ESTACIONAMIENTO
B29: 2 | C29: B-323 | D29: 3.08 | F29: 1 | G29: EV-23 | H29: 12.5 | I29: USO Y GOCE EXCLUSIVO | K29: 1 | L29: B-013 | M29: 4.79 | N29: BODEGA | P29: TOTAL EST SUB1 | R29: =SUM(R26:R27) -> 922.9
B30: 2 | C30: B-324 | D30: 3.19 | F30: 1 | G30: EV-24 | H30: 12.5 | I30: USO Y GOCE EXCLUSIVO | L30: E-39 | M30: 14.55 | N30: ESTACIONAMIENTO
B31: 2 | C31: B-325 | D31: =3.8-0.07 -> 3.73 | F31: 1 | G31: EV-25 | H31: 12.5 | I31: USO Y GOCE EXCLUSIVO | K31: 1 | L31: B-015 | M31: =5.08-0.21 -> 4.87 | N31: BODEGA | S31: SUBTE. -2
B32: 1 | C32: B-002 | D32: 5.21 | F32: 1 | G32: EV-26 | H32: 12.5 | I32: USO Y GOCE EXCLUSIVO | L32: E-42 | M32: 13.65 | N32: ESTACIONAMIENTO | P32: TOTAL BOD SUB2 INDV | R32: =SUM(D36:D37) -> 12.06
B33: 1 | C33: B-014 | D33: 5.14 | F33: 1 | G33: EV-27 | H33: 12.5 | I33: USO Y GOCE EXCLUSIVO | K33: 1 | L33: B-016 | M33: 4.88 | N33: BODEGA | P33: TOTAL BOD SUB2 CONJ | R33: =M91+M93+M95+M97+M99+M101+M103+M105+M107+M109+M111+M113+M115+M117+M119+M121+M123+M125+M127+M129+M131+M133+M135+M137+M139+M141+M143 -> 134.29
B34: -1 | C34: B-102 | D34: 3.82 | F34: 1 | G34: EV-28 | H34: 12.5 | I34: USO Y GOCE EXCLUSIVO | L34: E-43 | M34: 14.15 | N34: ESTACIONAMIENTO
B35: -1 | C35: B-116 | D35: 3.99 | F35: 1 | G35: EV-29 | H35: 12.5 | I35: USO Y GOCE EXCLUSIVO | K35: 1 | L35: B-017 | M35: =5.22-0.33 -> 4.89 | N35: BODEGA | P35: TOTAL BODEGAS SUB2 | R35: =SUM(R32:R33) -> 146.35
B36: -2 | C36: B-202 | D36: 6.98 | F36: 1 | G36: EV-30 | H36: 12.5 | I36: USO Y GOCE EXCLUSIVO | L36: E-44 | M36: 14 | N36: ESTACIONAMIENTO
B37: -2 | C37: B-229 | D37: 5.08 | F37: 1 | G37: EV-31 | H37: 12.5 | I37: USO Y GOCE EXCLUSIVO | K37: 1 | L37: B-018 | M37: 5.97 | N37: BODEGA | P37: TOTAL EST SUB2 INDV | R37: =SUM(H126:H174) -> 613.62
B38: -3 | C38: BC-01 | D38: 7.7 | F38: 1 | G38: EV-32 | H38: 12.5 | I38: USO Y GOCE EXCLUSIVO | L38: E-45 | M38: 12.67 | N38: ESTACIONAMIENTO | P38: TOTAL EST SUB2 CONJ | R38: =M92+M94+M96+M98+M100+M102+M104+M106+M108+M110+M112+M114+M116+M118+M120+M122+M124+M126+M128+M130+M132+M134+M136+M138+M140+M142+M144 -> 375.04
B39: -3 | C39: BC-02 | D39: 7.67 | F39: 1 | G39: EV-33 | H39: 12.5 | I39: USO Y GOCE EXCLUSIVO | K39: 1 | L39: B-019 | M39: =4.79-0.34 -> 4.45 | N39: BODEGA
B40: -3 | C40: BC-03 | D40: 7.6 | F40: 1 | G40: EV-34 | H40: 12.5 | I40: USO Y GOCE EXCLUSIVO | L40: E-46 | M40: 13.63 | N40: ESTACIONAMIENTO | P40: TOTAL EST SUB2 | R40: =SUM(R37:R38) -> 988.66
B41: -3 | C41: BC-04 | D41: 7.63 | F41: 1 | G41: EV-35 | H41: 12.5 | I41: USO Y GOCE EXCLUSIVO | K41: 1 | L41: B-020 | M41: =4.77-0.19 -> 4.58 | N41: BODEGA
B42: -3 | C42: BC-05 | D42: 7.63 | F42: 1 | G42: EV-36 | H42: 12.5 | I42: USO Y GOCE EXCLUSIVO | L42: E-47 | M42: 13.46 | N42: ESTACIONAMIENTO
B43: -3 | C43: BC-06 | D43: 7.6 | F43: 1 | G43: EV-37 | H43: 12.5 | I43: USO Y GOCE EXCLUSIVO | K43: -1 | L43: B-126 | M43: 5.5 | N43: BODEGA
B44: -3 | C44: BC-07 | D44: 7.67 | F44: 1 | G44: EV-38 | H44: 12.5 | I44: USO Y GOCE EXCLUSIVO | L44: E-084 | M44: 12.79 | N44: ESTACIONAMIENTO
B45: -3 | C45: BC-08 | D45: 7.7 | F45: 1 | G45: EV-39 | H45: 12.5 | I45: USO Y GOCE EXCLUSIVO | K45: -1 | L45: B-125 | M45: 5.94 | N45: BODEGA
B46: -3 | C46: BC-09 | D46: 9.81 | F46: 1 | G46: E-01 | H46: 12.5 | I46: ROL ASIGNADO | L46: E-085 | M46: 12.92 | N46: ESTACIONAMIENTO
B47: -3 | C47: BC-10 | D47: 6.81 | F47: 1 | G47: E-02 | H47: 12.5 | I47: ROL ASIGNADO | K47: -1 | L47: B-124 | M47: 4.89 | N47: BODEGA
B48: -3 | C48: BC-11 | D48: 7.29 | F48: 1 | G48: E-03 | H48: 12.5 | I48: ROL ASIGNADO | L48: E-086 | M48: 13.65 | N48: ESTACIONAMIENTO
F49: 1 | G49: E-04 | H49: 12.5 | I49: ROL ASIGNADO | K49: -1 | L49: B-123 | M49: 5.07 | N49: BODEGA
F50: 1 | G50: E-05 | H50: 12.5 | I50: ROL ASIGNADO | L50: E-087 | M50: 14.15 | N50: ESTACIONAMIENTO
B51: TOTAL BODEGAS DPTO | D51: =SUM(D7:D37) -> 112.98 | F51: 1 | G51: E-06 | H51: 12.5 | I51: ROL ASIGNADO | K51: -1 | L51: B-122 | M51: 5.21 | N51: BODEGA
F52: 1 | G52: E-07 | H52: 12.5 | I52: ROL ASIGNADO | L52: E-088 | M52: 14 | N52: ESTACIONAMIENTO
B53: TOTAL BODEGAS LC | D53: =SUM(D38:D48) -> 85.11 | F53: 1 | G53: E-08 | H53: 12.5 | I53: ROL ASIGNADO | K53: -1 | L53: B-121 | M53: 5.03 | N53: BODEGA
F54: 1 | G54: E-09 | H54: 12.5 | I54: ROL ASIGNADO | L54: E-089 | M54: 13.46 | N54: ESTACIONAMIENTO
B55: TOTAL BODEGAS | D55: =D51+D53 -> 198.09 | F55: 1 | G55: E-10 | H55: 12.5 | I55: ROL ASIGNADO | K55: -1 | L55: B-120 | M55: 4.83 | N55: BODEGA
F56: 1 | G56: E-11 | H56: 12.5 | I56: ROL ASIGNADO | L56: E-90 | M56: 13.46 | N56: ESTACIONAMIENTO
F57: 1 | G57: E-12 | H57: 12.5 | I57: ROL ASIGNADO | K57: -1 | L57: B-119 | M57: 4.83 | N57: BODEGA
B58: BODEGAS IND. PISO2 | D58: =COUNT(B7:B31) -> 25 | F58: 1 | G58: E-13 | H58: 12.5 | I58: ROL ASIGNADO | L58: E-091 | M58: 13.46 | N58: ESTACIONAMIENTO
F59: 1 | G59: E-14 | H59: 12.5 | I59: ROL ASIGNADO | K59: -1 | L59: B-118 | M59: 5.03 | N59: BODEGA
B60: BODEGAS IND. PISO1 | D60: =COUNT(B32:B33) -> 2 | F60: 1 | G60: E-15 | H60: 12.5 | I60: ROL ASIGNADO | L60: E-092 | M60: 13.46 | N60: ESTACIONAMIENTO
F61: 1 | G61: E-16 | H61: 12.5 | I61: ROL ASIGNADO | K61: -1 | L61: B-117 | M61: 5.32 | N61: BODEGA
B62: BODEGAS IND. PISO -1 | D62: =COUNT(B34:B35) -> 2 | F62: 1 | G62: E-17 | H62: 12.5 | I62: ROL ASIGNADO | L62: E-093 | M62: 13.5 | N62: ESTACIONAMIENTO
F63: 1 | G63: E-18 | H63: 12.5 | I63: ROL ASIGNADO | K63: -1 | L63: B-115 | M63: 4.56 | N63: BODEGA
B64: BODEGAS IND. PISO -2 | D64: =COUNT(B36:B37) -> 2 | F64: 1 | G64: E-19 | H64: 12.5 | I64: ROL ASIGNADO | L64: E-094 | M64: 16.35 | N64: ESTACIONAMIENTO
F65: 1 | G65: E-20 | H65: 12.5 | I65: ROL ASIGNADO | K65: -1 | L65: B-114 | M65: 6.6 | N65: BODEGA
B66: BODEGAS IND. PISO -3 | D66: =COUNT(B38:B48) -> 11 | F66: 1 | G66: E-21 | H66: 12.5 | I66: ROL ASIGNADO | L66: E-095 | M66: 14.1 | N66: ESTACIONAMIENTO
F67: 1 | G67: E-22 | H67: 12.5 | I67: ROL ASIGNADO | K67: -1 | L67: B-113 | M67: 6.73 | N67: BODEGA
B68: TOTAL BODEGAS IND. | D68: =SUM(D58:D66) -> 42 | F68: 1 | G68: E-23 | H68: 12.5 | I68: ROL ASIGNADO | L68: E-096 | M68: =2.75*5 -> 13.75 | N68: ESTACIONAMIENTO
F69: 1 | G69: E-24 | H69: 18 | I69: ROL ASIGNADO | K69: -1 | L69: B-112 | M69: 6.73 | N69: BODEGA
F70: 1 | G70: E-26 | H70: =17.12-0.31 -> 16.81 | I70: ROL ASIGNADO | L70: E-097 | M70: =2.75*5 -> 13.75 | N70: ESTACIONAMIENTO
F71: 1 | G71: E-37 | H71: =15.48-0.14 -> 15.34 | I71: ROL ASIGNADO | K71: -1 | L71: B-111 | M71: 6.6 | N71: BODEGA
F72: 1 | G72: E-38 | H72: =14.55-0.31 -> 14.24 | I72: ROL ASIGNADO | L72: E-098 | M72: =2.75*5 -> 13.75 | N72: ESTACIONAMIENTO
F73: 1 | G73: E-40 | H73: =18.38-0.06 -> 18.32 | I73: ROL ASIGNADO | K73: -1 | L73: B-110 | M73: 4.02 | N73: BODEGA
F74: 1 | G74: E-41 | H74: =17.41-0.16 -> 17.25 | I74: ROL ASIGNADO | L74: E-099 | M74: 13.5 | N74: ESTACIONAMIENTO
F75: 1 | G75: E-48 | H75: 12.5 | I75: ROL ASIGNADO | K75: -1 | L75: B-109 | M75: 3.89 | N75: BODEGA
F76: 1 | G76: E-49 | H76: 12.5 | I76: ROL ASIGNADO | L76: E-100 | M76: 14.05 | N76: ESTACIONAMIENTO
F77: 1 | G77: E-50 | H77: 12.5 | I77: ROL ASIGNADO | K77: -1 | L77: B108 | M77: 3.37 | N77: BODEGA
F78: 1 | G78: E-51 | H78: 18 | I78: ROL ASIGNADO | L78: E-101 | M78: 14.11 | N78: ESTACIONAMIENTO
F79: -1 | G79: E-61 | H79: 12.5 | I79: ROL ASIGNADO | K79: -1 | L79: B-107 | M79: 3.37 | N79: BODEGA
F80: -1 | G80: E-62 | H80: 12.42 | I80: ROL ASIGNADO | L80: E-102 | M80: 14.11 | N80: ESTACIONAMIENTO
F81: -1 | G81: E-63 | H81: 12.42 | I81: ROL ASIGNADO | K81: -1 | L81: B-106 | M81: 3.89 | N81: BODEGA
F82: -1 | G82: E-64 | H82: 12.5 | I82: ROL ASIGNADO | L82: E-103 | M82: 14.11 | N82: ESTACIONAMIENTO
F83: -1 | G83: E-65 | H83: 12.42 | I83: ROL ASIGNADO | K83: -1 | L83: B-105 | M83: 3.73 | N83: BODEGA
F84: -1 | G84: E-66 | H84: 12.42 | I84: ROL ASIGNADO | L84: E-104 | M84: 14.05 | N84: ESTACIONAMIENTO
F85: -1 | G85: E-67 | H85: 12.5 | I85: ROL ASIGNADO | K85: -1 | L85: B-104 | M85: 3.95 | N85: BODEGA
F86: -1 | G86: E-68 | H86: 12.42 | I86: ROL ASIGNADO | L86: E-105 | M86: 14.22 | N86: ESTACIONAMIENTO
F87: -1 | G87: E-69 | H87: 12.42 | I87: ROL ASIGNADO | K87: -1 | L87: B-103 | M87: 3.79 | N87: BODEGA
F88: -1 | G88: E-70 | H88: 12.5 | I88: ROL ASIGNADO | L88: E-106 | M88: 13.72 | N88: ESTACIONAMIENTO
F89: -1 | G89: E-71 | H89: 12.42 | I89: ROL ASIGNADO | K89: -1 | L89: B-101 | M89: 3.79 | N89: BODEGA
F90: -1 | G90: E-72 | H90: 12.42 | I90: ROL ASIGNADO | L90: E-107 | M90: 15.86 | N90: ESTACIONAMIENTO
F91: -1 | G91: E-73 | H91: 12.5 | I91: ROL ASIGNADO | K91: -2 | L91: B-228 | M91: 5.5 | N91: BODEGA
F92: -1 | G92: E-74 | H92: 12.42 | I92: ROL ASIGNADO | L92: E-155 | M92: 12.81 | N92: ESTACIONAMIENTO
F93: -1 | G93: E-75 | H93: 12.42 | I93: ROL ASIGNADO | K93: -2 | L93: B-227 | M93: 5.86 | N93: BODEGA
F94: -1 | G94: E-76 | H94: 12.5 | I94: ROL ASIGNADO | L94: E-156 | M94: 12.9 | N94: ESTACIONAMIENTO
F95: -1 | G95: E-77 | H95: 12.42 | I95: ROL ASIGNADO | K95: -2 | L95: B-226 | M95: 4.89 | N95: BODEGA
F96: -1 | G96: E-78 | H96: 12.42 | I96: ROL ASIGNADO | L96: E-157 | M96: 13.65 | N96: ESTACIONAMIENTO
F97: -1 | G97: E-79 | H97: 12.5 | I97: ROL ASIGNADO | K97: -2 | L97: B-225 | M97: 5.28 | N97: BODEGA
F98: -1 | G98: E-80 | H98: 12.42 | I98: ROL ASIGNADO | L98: E-158 | M98: 14.15 | N98: ESTACIONAMIENTO
F99: -1 | G99: E-81 | H99: 12.42 | I99: ROL ASIGNADO | K99: -2 | L99: B-224 | M99: 5.02 | N99: BODEGA
F100: -1 | G100: E-82 | H100: 12.5 | I100: ROL ASIGNADO | L100: E-159 | M100: 14 | N100: ESTACIONAMIENTO
F101: -1 | G101: E-83 | H101: 12.5 | I101: ROL ASIGNADO | K101: -2 | L101: B-223 | M101: 5.9 | N101: BODEGA
F102: -1 | G102: E-108 | H102: 15.86 | I102: ROL ASIGNADO | L102: E-160 | M102: 18.17 | N102: EST.MINUSVALIDO
...

Sheet INFO CONCON
O80: sumatorio longuitudes en metros de las curvas | P80: =20.53+38.68+59.03+79.05+97.7+104.07+135.54+136.84+140.61+142.34+194.98+168.58+138.41+113.51+115.26+112.05+104.84+104+102.86+101.67+89.93+87.87+85.79+83.91+82.58+81.38+80.15+78.65+76.21+82.2+24.93+53.64+15.21+51.32 -> 3184.32
O83: s=(IxLx100)/A | P83: =(0.5*P80*100)/5312 -> 29.972892

Sheet INFO COMERCIAL
T23: 237.32
T24: 277.59
T25: 0
T32: =SUM(T23:T31) -> 514.91
R35: 1 por cada 50m2 | T35: =T32/50 -> 10.2982 | U35: =T35 -> 10.2982
R37: 1 por cada 100m2 | T37: =T32/100 -> 5.1491 | U37: =T37 -> 5.1491

Sheet Evaluación V0
B2: Superficie terreno | D2: 5312 | E2: m2 | G2: PROPUESTA
B3: Area Afecta a Utilidad Publica | D3: 0 | E3: m2 | G3: N° de Pisos | H3: 22
B4: Superficie Neta | D4: 5312 | E4: m2 | G4: Altura piso 1° | H4: 2.52
B5: Constructibilidad max permitida | D5: 13811.2 | E5: m2 | G5: Altura piso tipo | H5: 2.52
B6: Superficie Media Calzada | D6: 2657.02 | E6: m2 | G6: Altura Subterraneo 1 | H6: 2.88
B7: Superficie para Densidad | D7: 7969.02 | E7: m2 | G7: Altura Subterraneo 2
B8: Numero de vivendas permitidas | D8: 195.24099 | E8: un | G8: Altura Subterraneo 3 | H8: -
B9: Media departamentos | D9: 70.739244 | E9: m2 | G9: Altura npt 1° Nivel acceso | H9: 0.15
G10: Altura total Edificio | H10: 55.44
G11: Altura a enterrarse | H11: 1.44
B12: Costos | G12: Altura total sobre N.T.N. | H12: 55
B14: Superficie total a construir | C14: 12346.83 | D14: m2
B15: Costo Construcció | C15: 22 | D15: UF | G15: Ingresos
B16: Total Construcción | C16: =C14*C15 -> 271630.26 | D16: UF | E16: Neto
G17: DEPTO-A | H17: DEPTO-B | I17: DEPTO-C1 | J17: DEPTO-C2 | K17: DEPTO-D | L17: DEPTO-E | M17: DEPTO-F
B18: Evaluación y Estudios | C18: 10000 | D18: UF | E18: Neto | G18: 38 | H18: 40 | I18: 19 | J18: 20 | K18: 39 | L18: 19 | M18: 20
G19: 1D+1B+K | H19: 2D+2B+K | I19: 2D+2B+K (MARIPOSA) | J19: 2D+2B+K (MARIPOSA) | K19: 2D+2B+K | L19: 3D+2B+K | M19: 2D+2B+K
B20: Comercialización | C20: 8000 | D20: UF | E20: Neto | G20: 33.24 | H20: 50.18 | I20: 50.18 | J20: 50.28 | K20: 57.67 | L20: 71.18 | M20: 60.68
G21: 2500 | H21: 4100 | I21: 4500 | J21: 4700 | K21: 5000 | L21: 6000 | M21: 5100
B22: Imprevistos | C22: 10000 | D22: UF | E22: Neto | G22: =G18*G21 -> 95000 | H22: =H18*H21 -> 164000 | I22: =I18*I21 -> 85500 | J22: =J18*J21 -> 94000 | K22: =K18*K21 -> 195000 | L22: =L18*L21 -> 114000 | M22: =M18*M21 -> 102000
B24: Total | C24: =C16+C18+C20+C22 -> 299630.26 | G24: Total Ingresos | H24: =G22+H22+I22+J22+K22+L22+M22 -> 849500
B26: Terreno | C26: 5312 | G26: Margen | H26: =H24-C30 -> 406445.74
B27: Valor Terreno | C27: 27
B28: Total Terreno | C28: =C26*C27 -> 143424
B30: Total Proyecto | C30: =C24+C28 -> 443054.26
